{
    "$schema": "https://schema.management.azure.com/schemas/2019-04-01/deploymentTemplate.json#",
    "contentVersion": "1.0.0.0",
    "parameters": {
        "sites_eventgridviewer_web_name": {
            "defaultValue": "eventgridviewer-web",
            "type": "String"
        },
        "serverfarms_eventgridviewer_plan_name": {
            "defaultValue": "eventgridviewer-plan",
            "type": "String"
        }
    },
    "variables": {},
    "resources": [
        {
            "type": "Microsoft.Web/serverfarms",
            "apiVersion": "2022-09-01",
            "name": "[parameters('serverfarms_eventgridviewer_plan_name')]",
            "location": "West US 2",
            "sku": {
                "name": "F1",
                "tier": "Free",
                "size": "F1",
                "family": "F",
                "capacity": 0
            },
            "kind": "app",
            "properties": {
                "perSiteScaling": false,
                "elasticScaleEnabled": false,
                "maximumElasticWorkerCount": 1,
                "isSpot": false,
                "reserved": false,
                "isXenon": false,
                "hyperV": false,
                "targetWorkerCount": 0,
                "targetWorkerSizeId": 0,
                "zoneRedundant": false
            }
        },
        {
            "type": "Microsoft.Web/sites",
            "apiVersion": "2022-09-01",
            "name": "[parameters('sites_eventgridviewer_web_name')]",
            "location": "West US 2",
            "dependsOn": [
                "[resourceId('Microsoft.Web/serverfarms', parameters('serverfarms_eventgridviewer_plan_name'))]"
            ],
            "kind": "app",
            "properties": {
                "enabled": true,
                "hostNameSslStates": [
                    {
                        "name": "[concat(parameters('sites_eventgridviewer_web_name'), '.azurewebsites.net')]",
                        "sslState": "Disabled",
                        "hostType": "Standard"
                    },
                    {
                        "name": "[concat(parameters('sites_eventgridviewer_web_name'), '.scm.azurewebsites.net')]",
                        "sslState": "Disabled",
                        "hostType": "Repository"
                    }
                ],
                "serverFarmId": "[resourceId('Microsoft.Web/serverfarms', parameters('serverfarms_eventgridviewer_plan_name'))]",
                "reserved": false,
                "isXenon": false,
                "hyperV": false,
                "vnetRouteAllEnabled": false,
                "vnetImagePullEnabled": false,
                "vnetContentShareEnabled": false,
                "siteConfig": {
                    "numberOfWorkers": 1,
                    "acrUseManagedIdentityCreds": false,
                    "alwaysOn": false,
                    "http20Enabled": false,
                    "functionAppScaleLimit": 0,
                    "minimumElasticInstanceCount": 0
                },
                "scmSiteAlsoStopped": false,
                "clientAffinityEnabled": true,
                "clientCertEnabled": false,
                "clientCertMode": "Required",
                "hostNamesDisabled": false,
                "customDomainVerificationId": "40BF7B86C2FCFDDFCAF1DB349DF5DEE2661093DBD1F889FA84ED4AAB4DA8B993",
                "containerSize": 0,
                "dailyMemoryTimeQuota": 0,
                "httpsOnly": true,
                "redundancyMode": "None",
                "storageAccountRequired": false,
                "keyVaultReferenceIdentity": "SystemAssigned"
            }
        },
        {
            "type": "Microsoft.Web/sites/basicPublishingCredentialsPolicies",
            "apiVersion": "2022-09-01",
            "name": "[concat(parameters('sites_eventgridviewer_web_name'), '/ftp')]",
            "location": "West US 2",
            "dependsOn": [
                "[resourceId('Microsoft.Web/sites', parameters('sites_eventgridviewer_web_name'))]"
            ],
            "properties": {
                "allow": true
            }
        },
        {
            "type": "Microsoft.Web/sites/basicPublishingCredentialsPolicies",
            "apiVersion": "2022-09-01",
            "name": "[concat(parameters('sites_eventgridviewer_web_name'), '/scm')]",
            "location": "West US 2",
            "dependsOn": [
                "[resourceId('Microsoft.Web/sites', parameters('sites_eventgridviewer_web_name'))]"
            ],
            "properties": {
                "allow": true
            }
        },
        {
            "type": "Microsoft.Web/sites/config",
            "apiVersion": "2022-09-01",
            "name": "[concat(parameters('sites_eventgridviewer_web_name'), '/web')]",
            "location": "West US 2",
            "dependsOn": [
                "[resourceId('Microsoft.Web/sites', parameters('sites_eventgridviewer_web_name'))]"
            ],
            "properties": {
                "numberOfWorkers": 1,
                "defaultDocuments": [
                    "Default.htm",
                    "Default.html",
                    "Default.asp",
                    "index.htm",
                    "index.html",
                    "iisstart.htm",
                    "default.aspx",
                    "index.php",
                    "hostingstart.html"
                ],
                "netFrameworkVersion": "v6.0",
                "phpVersion": "5.6",
                "requestTracingEnabled": false,
                "remoteDebuggingEnabled": false,
                "httpLoggingEnabled": false,
                "acrUseManagedIdentityCreds": false,
                "logsDirectorySizeLimit": 35,
                "detailedErrorLoggingEnabled": false,
                "publishingUsername": "$eventgridviewer-web",
                "scmType": "ExternalGit",
                "use32BitWorkerProcess": true,
                "webSocketsEnabled": true,
                "alwaysOn": false,
                "managedPipelineMode": "Integrated",
                "virtualApplications": [
                    {
                        "virtualPath": "/",
                        "physicalPath": "site\\wwwroot",
                        "preloadEnabled": false
                    }
                ],
                "loadBalancing": "LeastRequests",
                "experiments": {
                    "rampUpRules": []
                },
                "autoHealEnabled": false,
                "vnetRouteAllEnabled": false,
                "vnetPrivatePortsCount": 0,
                "localMySqlEnabled": false,
                "ipSecurityRestrictions": [
                    {
                        "ipAddress": "Any",
                        "action": "Allow",
                        "priority": 2147483647,
                        "name": "Allow all",
                        "description": "Allow all access"
                    }
                ],
                "scmIpSecurityRestrictions": [
                    {
                        "ipAddress": "Any",
                        "action": "Allow",
                        "priority": 2147483647,
                        "name": "Allow all",
                        "description": "Allow all access"
                    }
                ],
                "scmIpSecurityRestrictionsUseMain": false,
                "http20Enabled": false,
                "minTlsVersion": "1.2",
                "scmMinTlsVersion": "1.2",
                "ftpsState": "FtpsOnly",
                "preWarmedInstanceCount": 0,
                "elasticWebAppScaleLimit": 0,
                "functionsRuntimeScaleMonitoringEnabled": false,
                "minimumElasticInstanceCount": 0,
                "azureStorageAccounts": {}
            }
        },
        {
            "type": "Microsoft.Web/sites/deployments",
            "apiVersion": "2022-09-01",
            "name": "[concat(parameters('sites_eventgridviewer_web_name'), '/426440ffa752ab0bb2fdd052fe989717827e2ae7')]",
            "location": "West US 2",
            "dependsOn": [
                "[resourceId('Microsoft.Web/sites', parameters('sites_eventgridviewer_web_name'))]"
            ],
            "properties": {
                "status": 4,
                "author_email": "dabarkol@microsoft.com",
                "author": "David Barkol",
                "deployer": "GitHub",
                "message": "Merge pull request #21 from dbarkol/main\n\nUpgrade to .NET Core 6.0",
                "start_time": "2023-05-19T18:44:20.445519Z",
                "end_time": "2023-05-19T18:45:20.3752385Z",
                "active": true
            }
        },
        {
            "type": "Microsoft.Web/sites/hostNameBindings",
            "apiVersion": "2022-09-01",
            "name": "[concat(parameters('sites_eventgridviewer_web_name'), '/', parameters('sites_eventgridviewer_web_name'), '.azurewebsites.net')]",
            "location": "West US 2",
            "dependsOn": [
                "[resourceId('Microsoft.Web/sites', parameters('sites_eventgridviewer_web_name'))]"
            ],
            "properties": {
                "siteName": "eventgridviewer-web",
                "hostNameType": "Verified"
            }
        }
    ]
}